bm_configurator/__init__.py
bm_configurator/config.py
bm_configurator/configurator.py
bm_configurator-0.0.0.dist-info/METADATA
bm_configurator-0.0.0.dist-info/WHEEL
bm_configurator-0.0.0.dist-info/top_level.txt
bm_configurator-0.0.0.dist-info/RECORD
