Metadata-Version: 2.2
Name: bm_configurator
Version: 0.0.0
Summary: The configurator allows you to collect knowledge about models in configs and select among them suitable for local deployment on certain devices.
Home-page: https://github.com/Dmatryus/bm_configurator
Author: Dmatryus Datry
Author-email: dmatryus.sqrt49@yandex.ru
Classifier: Programming Language :: Python :: 3
Classifier: License :: OSI Approved :: MIT License
Classifier: Operating System :: OS Independent
Requires-Python: >=3.8
Requires-Dist: PyYAML>=5.4
Requires-Dist: psutil>=5.8
Requires-Dist: nvidia-ml-py>=12.535.77
Dynamic: author
Dynamic: author-email
Dynamic: classifier
Dynamic: description
Dynamic: description-content-type
Dynamic: home-page
Dynamic: requires-dist
Dynamic: requires-python
Dynamic: summary
